{
  "images": [
    {
      "id": 1,
      "url": "https://drive.google.com/file/d/1pKc29Pg9fzpKAMFA8fnbtEWc7f1NqTSn/view?usp=share_link",
      "comments": [
        {
          "id": 1,
          "date": "2021-07-01",
          "text": "Excellent",
          "userName": "AB123"
        },
        {
          "id": 2,
          "date": "2021-12-11",
          "text": "Nice",
          "userName": "PPP"
        }
      ]
    },
    {
      "id": 2,
      "url": "https://drive.google.com/file/d/1MhM9e4c-A6WsrJJo5aS309LLeHRyBfM4/view?usp=share_link",
      "comments": []
    },
    {
      "id": 3,
      "url": "https://drive.google.com/file/d/1qG4H2MOUzVwtvI5u4Dlf9ox7KfhmGxS0/view?usp=share_link",
      "comments": []
    },
    {
      "id": 4,
      "url": "https://drive.google.com/file/d/1l30kR5Topzv1YQWZIzneUzQBmkE9BErL/view?usp=share_link",
      "comments": []
    },
    {
      "id": 5,
      "url": "https://drive.google.com/file/d/1xZnbAZpF5AW67W8sp6K0ESDwTfE2newh/view?usp=share_link",
      "comments": [
        {
          "id": 1,
          "date": "2021-07-01",
          "text": "So beautiful",
          "userName": "User123"
        }
      ]
    },
    {
      "id": 6,
      "url": "https://drive.google.com/file/d/1yz9xWs5RDA7uOtqSG6werbAnrzo_wwq6/view?usp=share_link",
      "comments": []
    },
    {
      "id": 7,
      "url": "https://drive.google.com/file/d/1feq1gE0X6qPwWT5v1R3KU5x0vzxtHihA/view?usp=share_link",
      "comments": []
    },
    {
      "id": 8,
      "url": "https://drive.google.com/file/d/1Yon-GI001bO5uPCxRE9ls_Q_2Hz_Puy0/view?usp=share_link",
      "comments": []
    },
    {
      "id": 9,
      "url": "https://drive.google.com/file/d/1HRemkBsMwSXalkB_whhaXjfx-cVPm6dw/view?usp=share_link",
      "comments": [
        {
          "id": 1,
          "date": "2021-07-01",
          "text": "Great",
          "userName": "User777"
        }
      ]
    }
  ]
}
